nonebot_plugin_hotsearch/__init__.py
nonebot_plugin_hotsearch-0.1.1.dist-info/LICENSE.txt
nonebot_plugin_hotsearch-0.1.1.dist-info/METADATA
nonebot_plugin_hotsearch-0.1.1.dist-info/WHEEL
nonebot_plugin_hotsearch-0.1.1.dist-info/RECORD
