Metadata-Version: 2.1
Name: nonebot-plugin-hotsearch
Version: 0.1.1
Summary: nonebot2 plugin for hotsearch
License: MIT
Author: Astolfocat
Author-email: 2364934266@qq.com
Requires-Python: >=3.9,<4.0
Classifier: License :: OSI Approved :: MIT License
Classifier: Programming Language :: Python :: 3
Classifier: Programming Language :: Python :: 3.9
Classifier: Programming Language :: Python :: 3.10
Classifier: Programming Language :: Python :: 3.11
Requires-Dist: httpx (>=0.23.3,<0.24.0)
Requires-Dist: nonebot-adapter-onebot (>=2.1.3,<3.0.0)
Requires-Dist: nonebot2 (>=2.0.0-rc.3,<3.0.0)
